jupyter_server_terminals_proxy/__init__.py
jupyter_server_terminals_proxy/api_handlers.py
jupyter_server_terminals_proxy/app.py
jupyter_server_terminals_proxy/handlers.py
jupyter_server_terminals_proxy-0.2.1.data/data/etc/jupyter/jupyter_server_config.d/jupyter_server_terminals_proxy.json
jupyter_server_terminals_proxy-0.2.1.dist-info/METADATA
jupyter_server_terminals_proxy-0.2.1.dist-info/WHEEL
jupyter_server_terminals_proxy-0.2.1.dist-info/licenses/LICENSE
jupyter_server_terminals_proxy-0.2.1.dist-info/RECORD
